py_base_framework/__init__.py
py_base_framework/cloud_base_core.py
py_base_framework/cloud_base_exception.py
py_base_framework/cloud_base_log.py
py_base_framework-0.1.1.dist-info/LICENSE.LGPL
py_base_framework-0.1.1.dist-info/WHEEL
py_base_framework-0.1.1.dist-info/METADATA
py_base_framework-0.1.1.dist-info/RECORD
